[
  {
    "date": "2026-04-24T20:41:50.145234",
    "top_id": "s39",
    "bottom_id": "s27",
    "shoe_id": "s1",
    "outer_id": "s5"
  },
  {
    "date": "2026-04-25T20:34:10.920301",
    "top_id": "s32",
    "bottom_id": "s24",
    "shoe_id": "s1",
    "outer_id": "s14"
  },
  {
    "date": "2026-04-26T20:34:26.088365",
    "top_id": "s40",
    "bottom_id": "s21",
    "shoe_id": "s1",
    "outer_id": "s2"
  },
  {
    "date": "2026-04-27T20:57:46.210161",
    "top_id": "s28",
    "bottom_id": "s53",
    "shoe_id": "s1",
    "outer_id": "s6"
  },
  {
    "date": "2026-04-28T21:04:04.031383",
    "top_id": "s51",
    "bottom_id": "s35",
    "shoe_id": "s1",
    "outer_id": "s7"
  }
]